setuptools_lint/__init__.py
setuptools_lint/setuptools_command.py
setuptools_lint-0.6.0.dist-info/METADATA
setuptools_lint-0.6.0.dist-info/RECORD
setuptools_lint-0.6.0.dist-info/WHEEL
setuptools_lint-0.6.0.dist-info/entry_points.txt
setuptools_lint-0.6.0.dist-info/top_level.txt
