Metadata-Version: 2.1
Name: setuptools-lint
Version: 0.6.0
Summary: Setuptools command for pylint
Home-page: https://github.com/johnnoone/setuptools-pylint
Author: Xavier Barbosa
Author-email: UNKNOWN
License: BSD
Keywords: pylint setuptools command
Platform: UNKNOWN
Classifier: Topic :: Documentation
Classifier: Framework :: Setuptools Plugin
Classifier: Development Status :: 4 - Beta
Classifier: Intended Audience :: Developers
Classifier: Operating System :: OS Independent
Classifier: Programming Language :: Python :: 2
Classifier: Programming Language :: Python :: 3
Classifier: License :: OSI Approved :: BSD License
Classifier: Topic :: Software Development :: Documentation
Classifier: Topic :: Software Development :: Libraries :: Python Modules
Requires-Dist: pylint
